{
  "data": [
    {
      "HTML Attribute - Initial Findings": 0,
      "Color Contrast - Initial Findings": 9,
      "Missing Image Descriptions": 14,
      "agency": "U.S. Postal Service, Office of Inspector General",
      "Average Errors per Page": 23.0,
      "Form - Initial Findings": 0,
      "pages_count": 1
    },
    {
      "HTML Attribute - Initial Findings": 1,
      "Color Contrast - Initial Findings": 5.82,
      "Missing Image Descriptions": 2.27,
      "agency": "National Archives and Records Administration",
      "Average Errors per Page": 9.09,
      "Form - Initial Findings": 0,
      "pages_count": 11
    },
    {
      "HTML Attribute - Initial Findings": 3,
      "Color Contrast - Initial Findings": 8,
      "Missing Image Descriptions": 0,
      "agency": "Federal Mediation and Conciliation Service",
      "Average Errors per Page": 11.0,
      "Form - Initial Findings": 0,
      "pages_count": 1
    },
    {
      "HTML Attribute - Initial Findings": 0,
      "Color Contrast - Initial Findings": 0,
      "Missing Image Descriptions": 0,
      "agency": "Appraisal Subcommittee",
      "Average Errors per Page": 0.0,
      "Form - Initial Findings": 0,
      "pages_count": 1
    },
    {
      "HTML Attribute - Initial Findings": 0,
      "Color Contrast - Initial Findings": 0,
      "Missing Image Descriptions": 0,
      "agency": "Civil Air Patrol",
      "Average Errors per Page": 0.0,
      "Form - Initial Findings": 0,
      "pages_count": 1
    },
    {
      "HTML Attribute - Initial Findings": 4,
      "Color Contrast - Initial Findings": 0,
      "Missing Image Descriptions": 0,
      "agency": "Comm for People Who Are Blind/Severly Disabled",
      "Average Errors per Page": 4.0,
      "Form - Initial Findings": 0,
      "pages_count": 2
    },
    {
      "HTML Attribute - Initial Findings": 1,
      "Color Contrast - Initial Findings": 17,
      "Missing Image Descriptions": 0,
      "agency": "Federal Mine Safety and Health Review Company",
      "Average Errors per Page": 18.0,
      "Form - Initial Findings": 0,
      "pages_count": 1
    },
    {
      "HTML Attribute - Initial Findings": 0,
      "Color Contrast - Initial Findings": 0,
      "Missing Image Descriptions": 0,
      "agency": "National Endowment for the Arts",
      "Average Errors per Page": 0.0,
      "Form - Initial Findings": 0,
      "pages_count": 1
    },
    {
      "HTML Attribute - Initial Findings": 0,
      "Color Contrast - Initial Findings": 4,
      "Missing Image Descriptions": 0,
      "agency": "Institute of Museum and Library Services",
      "Average Errors per Page": 4.0,
      "Form - Initial Findings": 0,
      "pages_count": 1
    },
    {
      "HTML Attribute - Initial Findings": 0,
      "Color Contrast - Initial Findings": 0,
      "Missing Image Descriptions": 0,
      "agency": "National Transportation Safety Board",
      "Average Errors per Page": 0.0,
      "Form - Initial Findings": 0,
      "pages_count": 1
    },
    {
      "HTML Attribute - Initial Findings": 0.8,
      "Color Contrast - Initial Findings": 5,
      "Missing Image Descriptions": 1.3,
      "agency": "Federal Trade Commission",
      "Average Errors per Page": 7.1,
      "Form - Initial Findings": 0,
      "pages_count": 10
    },
    {
      "HTML Attribute - Initial Findings": 1.14,
      "Color Contrast - Initial Findings": 2.05,
      "Missing Image Descriptions": 1.38,
      "agency": "Department of Agriculture",
      "Average Errors per Page": 4.57,
      "Form - Initial Findings": 0,
      "pages_count": 21
    },
    {
      "HTML Attribute - Initial Findings": 0,
      "Color Contrast - Initial Findings": 0,
      "Missing Image Descriptions": 0,
      "agency": "Railroad Retirement Board",
      "Average Errors per Page": 0.0,
      "Form - Initial Findings": 0,
      "pages_count": 1
    },
    {
      "HTML Attribute - Initial Findings": 0,
      "Color Contrast - Initial Findings": 0,
      "Missing Image Descriptions": 19,
      "agency": "Central Intelligence Agency",
      "Average Errors per Page": 19.0,
      "Form - Initial Findings": 0,
      "pages_count": 2
    },
    {
      "HTML Attribute - Initial Findings": 1,
      "Color Contrast - Initial Findings": 9,
      "Missing Image Descriptions": 1.5,
      "agency": "National Endowment for the Humanities",
      "Average Errors per Page": 11.5,
      "Form - Initial Findings": 0,
      "pages_count": 2
    },
    {
      "HTML Attribute - Initial Findings": 0.71,
      "Color Contrast - Initial Findings": 9.57,
      "Missing Image Descriptions": 0,
      "agency": "U.S. Agency for International Development",
      "Average Errors per Page": 10.29,
      "Form - Initial Findings": 0,
      "pages_count": 7
    },
    {
      "HTML Attribute - Initial Findings": 5.25,
      "Color Contrast - Initial Findings": 7.5,
      "Missing Image Descriptions": 0,
      "agency": "Court Services and Offender Supervision",
      "Average Errors per Page": 12.75,
      "Form - Initial Findings": 0,
      "pages_count": 4
    },
    {
      "HTML Attribute - Initial Findings": 2,
      "Color Contrast - Initial Findings": 41,
      "Missing Image Descriptions": 1,
      "agency": "Tennessee Valley Authority",
      "Average Errors per Page": 44.0,
      "Form - Initial Findings": 0,
      "pages_count": 1
    },
    {
      "HTML Attribute - Initial Findings": 2.2,
      "Color Contrast - Initial Findings": 10,
      "Missing Image Descriptions": 2.4,
      "agency": "Corporation for National & Community Service",
      "Average Errors per Page": 14.6,
      "Form - Initial Findings": 0,
      "pages_count": 5
    },
    {
      "HTML Attribute - Initial Findings": 1.5,
      "Color Contrast - Initial Findings": 0.5,
      "Missing Image Descriptions": 5.5,
      "agency": "U. S. Postal Service",
      "Average Errors per Page": 7.5,
      "Form - Initial Findings": 0,
      "pages_count": 2
    },
    {
      "HTML Attribute - Initial Findings": 17,
      "Color Contrast - Initial Findings": 0,
      "Missing Image Descriptions": 12,
      "agency": "U.S. Chemical Safety and Hazard Investigation Board",
      "Average Errors per Page": 29.0,
      "Form - Initial Findings": 0,
      "pages_count": 1
    },
    {
      "HTML Attribute - Initial Findings": 18,
      "Color Contrast - Initial Findings": 5,
      "Missing Image Descriptions": 0,
      "agency": "U. S. Peace Corps",
      "Average Errors per Page": 23.0,
      "Form - Initial Findings": 0,
      "pages_count": 1
    },
    {
      "HTML Attribute - Initial Findings": 0,
      "Color Contrast - Initial Findings": 0,
      "Missing Image Descriptions": 6.5,
      "agency": "Federal Energy Regulatory Commission",
      "Average Errors per Page": 6.5,
      "Form - Initial Findings": 0,
      "pages_count": 2
    },
    {
      "HTML Attribute - Initial Findings": 0,
      "Color Contrast - Initial Findings": 0,
      "Missing Image Descriptions": 0,
      "agency": "Federal Housing Finance Agency",
      "Average Errors per Page": 0.0,
      "Form - Initial Findings": 0,
      "pages_count": 2
    },
    {
      "HTML Attribute - Initial Findings": 0.42,
      "Color Contrast - Initial Findings": 2.65,
      "Missing Image Descriptions": 1.24,
      "agency": "Department of the Treasury",
      "Average Errors per Page": 4.31,
      "Form - Initial Findings": 0,
      "pages_count": 72
    },
    {
      "HTML Attribute - Initial Findings": 5,
      "Color Contrast - Initial Findings": 0,
      "Missing Image Descriptions": 2,
      "agency": "National Nuclear Security Administration",
      "Average Errors per Page": 7.0,
      "Form - Initial Findings": 0,
      "pages_count": 1
    },
    {
      "HTML Attribute - Initial Findings": 1.5,
      "Color Contrast - Initial Findings": 6,
      "Missing Image Descriptions": 0,
      "agency": "Securities and Exchange Commission",
      "Average Errors per Page": 7.5,
      "Form - Initial Findings": 0,
      "pages_count": 2
    },
    {
      "HTML Attribute - Initial Findings": 12,
      "Color Contrast - Initial Findings": 11,
      "Missing Image Descriptions": 11,
      "agency": "U.S. Trade and Development Agency",
      "Average Errors per Page": 34.0,
      "Form - Initial Findings": 0,
      "pages_count": 1
    },
    {
      "HTML Attribute - Initial Findings": 3.67,
      "Color Contrast - Initial Findings": 3.17,
      "Missing Image Descriptions": 5.33,
      "agency": "National Science Foundation",
      "Average Errors per Page": 12.17,
      "Form - Initial Findings": 0,
      "pages_count": 6
    },
    {
      "HTML Attribute - Initial Findings": 0,
      "Color Contrast - Initial Findings": 4,
      "Missing Image Descriptions": 4,
      "agency": "Denali Commission",
      "Average Errors per Page": 8.0,
      "Form - Initial Findings": 0,
      "pages_count": 2
    },
    {
      "HTML Attribute - Initial Findings": 1.47,
      "Color Contrast - Initial Findings": 2.07,
      "Missing Image Descriptions": 3.8,
      "agency": "Department of Homeland Security",
      "Average Errors per Page": 7.33,
      "Form - Initial Findings": 0,
      "pages_count": 15
    },
    {
      "HTML Attribute - Initial Findings": 0,
      "Color Contrast - Initial Findings": 20,
      "Missing Image Descriptions": 2,
      "agency": "Federal Maritime Commission",
      "Average Errors per Page": 22.0,
      "Form - Initial Findings": 0,
      "pages_count": 1
    },
    {
      "HTML Attribute - Initial Findings": 0.14,
      "Color Contrast - Initial Findings": 10.93,
      "Missing Image Descriptions": 0.36,
      "agency": "Office of Personnel Management",
      "Average Errors per Page": 11.43,
      "Form - Initial Findings": 0,
      "pages_count": 14
    },
    {
      "HTML Attribute - Initial Findings": 0,
      "Color Contrast - Initial Findings": 1,
      "Missing Image Descriptions": 0,
      "agency": "Surface Transportation Board (STB)",
      "Average Errors per Page": 1.0,
      "Form - Initial Findings": 0,
      "pages_count": 1
    },
    {
      "HTML Attribute - Initial Findings": 1.72,
      "Color Contrast - Initial Findings": 6.12,
      "Missing Image Descriptions": 2,
      "agency": "Department of Energy",
      "Average Errors per Page": 9.84,
      "Form - Initial Findings": 0,
      "pages_count": 32
    },
    {
      "HTML Attribute - Initial Findings": 0.11,
      "Color Contrast - Initial Findings": 2.11,
      "Missing Image Descriptions": 0,
      "agency": "Department of Education",
      "Average Errors per Page": 2.22,
      "Form - Initial Findings": 0,
      "pages_count": 9
    },
    {
      "HTML Attribute - Initial Findings": 1,
      "Color Contrast - Initial Findings": 4,
      "Missing Image Descriptions": 0,
      "agency": "Legal Services Corporation",
      "Average Errors per Page": 5.0,
      "Form - Initial Findings": 0,
      "pages_count": 1
    },
    {
      "HTML Attribute - Initial Findings": 0,
      "Color Contrast - Initial Findings": 24,
      "Missing Image Descriptions": 0,
      "agency": "Merit Systems Protection Board",
      "Average Errors per Page": 24.0,
      "Form - Initial Findings": 0,
      "pages_count": 1
    },
    {
      "HTML Attribute - Initial Findings": 0,
      "Color Contrast - Initial Findings": 4,
      "Missing Image Descriptions": 0,
      "agency": "National Nanotechnology Coordination Office",
      "Average Errors per Page": 4.0,
      "Form - Initial Findings": 0,
      "pages_count": 1
    },
    {
      "HTML Attribute - Initial Findings": 12,
      "Color Contrast - Initial Findings": 4,
      "Missing Image Descriptions": 5,
      "agency": "African Development Foundation",
      "Average Errors per Page": 21.0,
      "Form - Initial Findings": 0,
      "pages_count": 2
    },
    {
      "HTML Attribute - Initial Findings": 0,
      "Color Contrast - Initial Findings": 0,
      "Missing Image Descriptions": 0,
      "agency": "American Battle Monuments Commission",
      "Average Errors per Page": 0.0,
      "Form - Initial Findings": 0,
      "pages_count": 1
    },
    {
      "HTML Attribute - Initial Findings": 0,
      "Color Contrast - Initial Findings": 14,
      "Missing Image Descriptions": 4,
      "agency": "National Indian Gaming Commission",
      "Average Errors per Page": 18.0,
      "Form - Initial Findings": 0,
      "pages_count": 1
    },
    {
      "HTML Attribute - Initial Findings": 13,
      "Color Contrast - Initial Findings": 2,
      "Missing Image Descriptions": 3,
      "agency": "International Broadcasting Bureau",
      "Average Errors per Page": 18.0,
      "Form - Initial Findings": 0,
      "pages_count": 1
    },
    {
      "HTML Attribute - Initial Findings": 0.33,
      "Color Contrast - Initial Findings": 2,
      "Missing Image Descriptions": 0.67,
      "agency": "National Aeronautics and Space Administration",
      "Average Errors per Page": 3.0,
      "Form - Initial Findings": 0,
      "pages_count": 3
    },
    {
      "HTML Attribute - Initial Findings": 0,
      "Color Contrast - Initial Findings": 0.5,
      "Missing Image Descriptions": 4,
      "agency": "Advisory Council on Historic Preservation",
      "Average Errors per Page": 4.5,
      "Form - Initial Findings": 0,
      "pages_count": 2
    },
    {
      "HTML Attribute - Initial Findings": 0,
      "Color Contrast - Initial Findings": 0,
      "Missing Image Descriptions": 0,
      "agency": "Consumer Financial Protection Bureau",
      "Average Errors per Page": 0.0,
      "Form - Initial Findings": 0,
      "pages_count": 1
    },
    {
      "HTML Attribute - Initial Findings": 0.52,
      "Color Contrast - Initial Findings": 3.92,
      "Missing Image Descriptions": 1.89,
      "agency": "Department of Health And Human Services",
      "Average Errors per Page": 6.34,
      "Form - Initial Findings": 0,
      "pages_count": 65
    },
    {
      "HTML Attribute - Initial Findings": 0,
      "Color Contrast - Initial Findings": 0,
      "Missing Image Descriptions": 0,
      "agency": "Medicaid and CHIP Payment and Access Commission",
      "Average Errors per Page": 0.0,
      "Form - Initial Findings": 0,
      "pages_count": 1
    },
    {
      "HTML Attribute - Initial Findings": 5.2,
      "Color Contrast - Initial Findings": 6.8,
      "Missing Image Descriptions": 4.2,
      "agency": "Consumer Product Safety Commission",
      "Average Errors per Page": 16.2,
      "Form - Initial Findings": 0,
      "pages_count": 5
    },
    {
      "HTML Attribute - Initial Findings": 0,
      "Color Contrast - Initial Findings": 0,
      "Missing Image Descriptions": 0,
      "agency": "Nuclear Regulatory Commission",
      "Average Errors per Page": 0.0,
      "Form - Initial Findings": 0,
      "pages_count": 1
    },
    {
      "HTML Attribute - Initial Findings": 4,
      "Color Contrast - Initial Findings": 9,
      "Missing Image Descriptions": 4,
      "agency": "Social Security Advisory Board",
      "Average Errors per Page": 17.0,
      "Form - Initial Findings": 0,
      "pages_count": 1
    },
    {
      "HTML Attribute - Initial Findings": 0,
      "Color Contrast - Initial Findings": 0,
      "Missing Image Descriptions": 0,
      "agency": "National Security Agency",
      "Average Errors per Page": 0.0,
      "Form - Initial Findings": 0,
      "pages_count": 2
    },
    {
      "HTML Attribute - Initial Findings": 0,
      "Color Contrast - Initial Findings": 0,
      "Missing Image Descriptions": 0,
      "agency": "U.S. Commission of Fine Arts",
      "Average Errors per Page": 0.0,
      "Form - Initial Findings": 0,
      "pages_count": 1
    },
    {
      "HTML Attribute - Initial Findings": 0,
      "Color Contrast - Initial Findings": 0,
      "Missing Image Descriptions": 0,
      "agency": "National Mediation Board",
      "Average Errors per Page": 0.0,
      "Form - Initial Findings": 0,
      "pages_count": 1
    },
    {
      "HTML Attribute - Initial Findings": 0,
      "Color Contrast - Initial Findings": 0.5,
      "Missing Image Descriptions": 4.5,
      "agency": "National Credit Union Administration",
      "Average Errors per Page": 5.0,
      "Form - Initial Findings": 0,
      "pages_count": 2
    },
    {
      "HTML Attribute - Initial Findings": 0,
      "Color Contrast - Initial Findings": 0,
      "Missing Image Descriptions": 0,
      "agency": "Armed Forces Retirement Home",
      "Average Errors per Page": 0.0,
      "Form - Initial Findings": 0,
      "pages_count": 1
    },
    {
      "HTML Attribute - Initial Findings": 0,
      "Color Contrast - Initial Findings": 7,
      "Missing Image Descriptions": 0,
      "agency": "United States Office of Government Ethics",
      "Average Errors per Page": 7.0,
      "Form - Initial Findings": 0,
      "pages_count": 1
    },
    {
      "HTML Attribute - Initial Findings": 12,
      "Color Contrast - Initial Findings": 33,
      "Missing Image Descriptions": 0,
      "agency": "National Gallery of Art",
      "Average Errors per Page": 45.0,
      "Form - Initial Findings": 0,
      "pages_count": 1
    },
    {
      "HTML Attribute - Initial Findings": 6,
      "Color Contrast - Initial Findings": 42,
      "Missing Image Descriptions": 0,
      "agency": "U. S. International Trade Commission",
      "Average Errors per Page": 48.0,
      "Form - Initial Findings": 0,
      "pages_count": 1
    },
    {
      "HTML Attribute - Initial Findings": 0.31,
      "Color Contrast - Initial Findings": 4.94,
      "Missing Image Descriptions": 3.12,
      "agency": "Department of State",
      "Average Errors per Page": 8.38,
      "Form - Initial Findings": 0,
      "pages_count": 16
    },
    {
      "HTML Attribute - Initial Findings": 0,
      "Color Contrast - Initial Findings": 12,
      "Missing Image Descriptions": 6,
      "agency": "Harry S. Truman Scholarship Foundation",
      "Average Errors per Page": 18.0,
      "Form - Initial Findings": 0,
      "pages_count": 1
    },
    {
      "HTML Attribute - Initial Findings": 2.67,
      "Color Contrast - Initial Findings": 7.71,
      "Missing Image Descriptions": 1.67,
      "agency": "Department of Defense",
      "Average Errors per Page": 12.05,
      "Form - Initial Findings": 0,
      "pages_count": 21
    },
    {
      "HTML Attribute - Initial Findings": 0,
      "Color Contrast - Initial Findings": 7,
      "Missing Image Descriptions": 0,
      "agency": "Federal Labor Relations Authority",
      "Average Errors per Page": 7.0,
      "Form - Initial Findings": 0,
      "pages_count": 1
    },
    {
      "HTML Attribute - Initial Findings": 0,
      "Color Contrast - Initial Findings": 4,
      "Missing Image Descriptions": 0,
      "agency": "Overseas Private Investment Corporation",
      "Average Errors per Page": 4.0,
      "Form - Initial Findings": 0,
      "pages_count": 1
    },
    {
      "HTML Attribute - Initial Findings": 0.33,
      "Color Contrast - Initial Findings": 0.67,
      "Missing Image Descriptions": 0.33,
      "agency": "Department of Veterans Affairs",
      "Average Errors per Page": 1.33,
      "Form - Initial Findings": 0,
      "pages_count": 3
    },
    {
      "HTML Attribute - Initial Findings": 0,
      "Color Contrast - Initial Findings": 5,
      "Missing Image Descriptions": 3,
      "agency": "Millennium Challenge Corporation",
      "Average Errors per Page": 8.0,
      "Form - Initial Findings": 0,
      "pages_count": 1
    },
    {
      "HTML Attribute - Initial Findings": 0,
      "Color Contrast - Initial Findings": 0,
      "Missing Image Descriptions": 2,
      "agency": "Federal Elections Commission",
      "Average Errors per Page": 2.0,
      "Form - Initial Findings": 0,
      "pages_count": 1
    },
    {
      "HTML Attribute - Initial Findings": 2,
      "Color Contrast - Initial Findings": 8,
      "Missing Image Descriptions": 27,
      "agency": "Networking Information Technology Research and Development (NITRD)",
      "Average Errors per Page": 37.0,
      "Form - Initial Findings": 0,
      "pages_count": 1
    },
    {
      "HTML Attribute - Initial Findings": 0,
      "Color Contrast - Initial Findings": 1.83,
      "Missing Image Descriptions": 0.5,
      "agency": "Director of National Intelligence",
      "Average Errors per Page": 2.33,
      "Form - Initial Findings": 0,
      "pages_count": 6
    },
    {
      "HTML Attribute - Initial Findings": 1,
      "Color Contrast - Initial Findings": 4,
      "Missing Image Descriptions": 2,
      "agency": "James Madison Memorial Fellowship Foundation",
      "Average Errors per Page": 7.0,
      "Form - Initial Findings": 0,
      "pages_count": 1
    },
    {
      "HTML Attribute - Initial Findings": 0,
      "Color Contrast - Initial Findings": 0,
      "Missing Image Descriptions": 0,
      "agency": "Federal Housing Finance Agency Office of Inspector General",
      "Average Errors per Page": 0.0,
      "Form - Initial Findings": 0,
      "pages_count": 1
    },
    {
      "HTML Attribute - Initial Findings": 0,
      "Color Contrast - Initial Findings": 0,
      "Missing Image Descriptions": 0,
      "agency": "U. S. Office of Special Counsel",
      "Average Errors per Page": 0.0,
      "Form - Initial Findings": 0,
      "pages_count": 1
    },
    {
      "HTML Attribute - Initial Findings": 0.33,
      "Color Contrast - Initial Findings": 2.2,
      "Missing Image Descriptions": 0.83,
      "agency": "Department of Justice",
      "Average Errors per Page": 3.37,
      "Form - Initial Findings": 0,
      "pages_count": 30
    },
    {
      "HTML Attribute - Initial Findings": 0,
      "Color Contrast - Initial Findings": 0.62,
      "Missing Image Descriptions": 0.5,
      "agency": "Environmental Protection Agency",
      "Average Errors per Page": 1.12,
      "Form - Initial Findings": 0,
      "pages_count": 8
    },
    {
      "HTML Attribute - Initial Findings": 0,
      "Color Contrast - Initial Findings": 0,
      "Missing Image Descriptions": 0,
      "agency": "National Capital Planning Commission",
      "Average Errors per Page": 0.0,
      "Form - Initial Findings": 0,
      "pages_count": 1
    },
    {
      "HTML Attribute - Initial Findings": 0.67,
      "Color Contrast - Initial Findings": 2.33,
      "Missing Image Descriptions": 0,
      "agency": "Federal Reserve System",
      "Average Errors per Page": 3.0,
      "Form - Initial Findings": 0,
      "pages_count": 6
    },
    {
      "HTML Attribute - Initial Findings": 2,
      "Color Contrast - Initial Findings": 2,
      "Missing Image Descriptions": 0,
      "agency": "AMTRAK",
      "Average Errors per Page": 4.0,
      "Form - Initial Findings": 0,
      "pages_count": 1
    },
    {
      "HTML Attribute - Initial Findings": 0,
      "Color Contrast - Initial Findings": 0,
      "Missing Image Descriptions": 0,
      "agency": "Commodity Futures Trading Commission",
      "Average Errors per Page": 0.0,
      "Form - Initial Findings": 0,
      "pages_count": 1
    },
    {
      "HTML Attribute - Initial Findings": 5.17,
      "Color Contrast - Initial Findings": 4.31,
      "Missing Image Descriptions": 1.95,
      "agency": "Department of the Interior",
      "Average Errors per Page": 11.43,
      "Form - Initial Findings": 0,
      "pages_count": 58
    },
    {
      "HTML Attribute - Initial Findings": 0,
      "Color Contrast - Initial Findings": 0,
      "Missing Image Descriptions": 0,
      "agency": "Office of Government Ethics",
      "Average Errors per Page": 0.0,
      "Form - Initial Findings": 0,
      "pages_count": 1
    },
    {
      "HTML Attribute - Initial Findings": 0,
      "Color Contrast - Initial Findings": 26,
      "Missing Image Descriptions": 3,
      "agency": "United Stated Global Change Research Program",
      "Average Errors per Page": 29.0,
      "Form - Initial Findings": 0,
      "pages_count": 1
    },
    {
      "HTML Attribute - Initial Findings": 6,
      "Color Contrast - Initial Findings": 24,
      "Missing Image Descriptions": 4,
      "agency": "US Interagency Council on Homelessness",
      "Average Errors per Page": 34.0,
      "Form - Initial Findings": 0,
      "pages_count": 1
    },
    {
      "HTML Attribute - Initial Findings": 6,
      "Color Contrast - Initial Findings": 0,
      "Missing Image Descriptions": 26,
      "agency": "Delta Regional Authority",
      "Average Errors per Page": 32.0,
      "Form - Initial Findings": 0,
      "pages_count": 1
    },
    {
      "HTML Attribute - Initial Findings": 10.2,
      "Color Contrast - Initial Findings": 7.2,
      "Missing Image Descriptions": 6.4,
      "agency": "Federal Deposit Insurance Corporation",
      "Average Errors per Page": 23.8,
      "Form - Initial Findings": 0,
      "pages_count": 5
    },
    {
      "HTML Attribute - Initial Findings": 0,
      "Color Contrast - Initial Findings": 0,
      "Missing Image Descriptions": 0,
      "agency": "Inter-American Foundation",
      "Average Errors per Page": 0.0,
      "Form - Initial Findings": 0,
      "pages_count": 1
    },
    {
      "HTML Attribute - Initial Findings": 0.59,
      "Color Contrast - Initial Findings": 2.73,
      "Missing Image Descriptions": 2.51,
      "agency": "General Services Administration",
      "Average Errors per Page": 5.83,
      "Form - Initial Findings": 0,
      "pages_count": 63
    },
    {
      "HTML Attribute - Initial Findings": 0,
      "Color Contrast - Initial Findings": 2,
      "Missing Image Descriptions": 0,
      "agency": "Appalachian Regional Commission",
      "Average Errors per Page": 2.0,
      "Form - Initial Findings": 0,
      "pages_count": 1
    },
    {
      "HTML Attribute - Initial Findings": 0,
      "Color Contrast - Initial Findings": 13,
      "Missing Image Descriptions": 2,
      "agency": "Postal Rate Commission",
      "Average Errors per Page": 15.0,
      "Form - Initial Findings": 0,
      "pages_count": 1
    },
    {
      "HTML Attribute - Initial Findings": 4,
      "Color Contrast - Initial Findings": 51,
      "Missing Image Descriptions": 7,
      "agency": "National Labor Relations Board",
      "Average Errors per Page": 62.0,
      "Form - Initial Findings": 0,
      "pages_count": 1
    },
    {
      "HTML Attribute - Initial Findings": 1.67,
      "Color Contrast - Initial Findings": 9.33,
      "Missing Image Descriptions": 0.33,
      "agency": "Small Business Administration",
      "Average Errors per Page": 11.33,
      "Form - Initial Findings": 0,
      "pages_count": 3
    },
    {
      "HTML Attribute - Initial Findings": 1.45,
      "Color Contrast - Initial Findings": 2.82,
      "Missing Image Descriptions": 2.91,
      "agency": "Executive Office of the President",
      "Average Errors per Page": 7.18,
      "Form - Initial Findings": 0,
      "pages_count": 11
    },
    {
      "HTML Attribute - Initial Findings": 1.13,
      "Color Contrast - Initial Findings": 3.24,
      "Missing Image Descriptions": 3.29,
      "agency": "Department of Commerce",
      "Average Errors per Page": 7.66,
      "Form - Initial Findings": 0,
      "pages_count": 38
    },
    {
      "HTML Attribute - Initial Findings": 1,
      "Color Contrast - Initial Findings": 14,
      "Missing Image Descriptions": 1,
      "agency": "U.S. Commission on Civil Rights",
      "Average Errors per Page": 16.0,
      "Form - Initial Findings": 0,
      "pages_count": 1
    },
    {
      "HTML Attribute - Initial Findings": 2,
      "Color Contrast - Initial Findings": 10,
      "Missing Image Descriptions": 0,
      "agency": "National Council on Disability",
      "Average Errors per Page": 12.0,
      "Form - Initial Findings": 0,
      "pages_count": 1
    },
    {
      "HTML Attribute - Initial Findings": 0,
      "Color Contrast - Initial Findings": 6,
      "Missing Image Descriptions": 0,
      "agency": "Smithsonian Institution",
      "Average Errors per Page": 6.0,
      "Form - Initial Findings": 0,
      "pages_count": 1
    },
    {
      "HTML Attribute - Initial Findings": 0,
      "Color Contrast - Initial Findings": 0,
      "Missing Image Descriptions": 0,
      "agency": "Selective Service System",
      "Average Errors per Page": 0.0,
      "Form - Initial Findings": 0,
      "pages_count": 1
    },
    {
      "HTML Attribute - Initial Findings": 0,
      "Color Contrast - Initial Findings": 0,
      "Missing Image Descriptions": 0,
      "agency": "Marine Mammal Commission",
      "Average Errors per Page": 0.0,
      "Form - Initial Findings": 0,
      "pages_count": 1
    },
    {
      "HTML Attribute - Initial Findings": 0,
      "Color Contrast - Initial Findings": 2,
      "Missing Image Descriptions": 0,
      "agency": "Social Security Administration",
      "Average Errors per Page": 2.0,
      "Form - Initial Findings": 0,
      "pages_count": 1
    },
    {
      "HTML Attribute - Initial Findings": 0,
      "Color Contrast - Initial Findings": 33,
      "Missing Image Descriptions": 1,
      "agency": "Morris K. Udall Foundation",
      "Average Errors per Page": 34.0,
      "Form - Initial Findings": 0,
      "pages_count": 1
    },
    {
      "HTML Attribute - Initial Findings": 0,
      "Color Contrast - Initial Findings": 1.5,
      "Missing Image Descriptions": 0,
      "agency": "Federal Retirement Thrift Investment Board",
      "Average Errors per Page": 1.5,
      "Form - Initial Findings": 0,
      "pages_count": 2
    },
    {
      "HTML Attribute - Initial Findings": 0,
      "Color Contrast - Initial Findings": 0,
      "Missing Image Descriptions": 0,
      "agency": "Administrative Conference of the United States",
      "Average Errors per Page": 0.0,
      "Form - Initial Findings": 0,
      "pages_count": 1
    },
    {
      "HTML Attribute - Initial Findings": 1.27,
      "Color Contrast - Initial Findings": 6.6,
      "Missing Image Descriptions": 0.6,
      "agency": "Department of Transportation",
      "Average Errors per Page": 8.47,
      "Form - Initial Findings": 0,
      "pages_count": 15
    },
    {
      "HTML Attribute - Initial Findings": 3.5,
      "Color Contrast - Initial Findings": 5,
      "Missing Image Descriptions": 0.5,
      "agency": "Council of Inspector General on Integrity and Efficiency",
      "Average Errors per Page": 9.0,
      "Form - Initial Findings": 0,
      "pages_count": 2
    },
    {
      "HTML Attribute - Initial Findings": 0,
      "Color Contrast - Initial Findings": 0,
      "Missing Image Descriptions": 0,
      "agency": "U. S. Access Board",
      "Average Errors per Page": 0.0,
      "Form - Initial Findings": 0,
      "pages_count": 1
    },
    {
      "HTML Attribute - Initial Findings": 0,
      "Color Contrast - Initial Findings": 0,
      "Missing Image Descriptions": 1,
      "agency": "Occupational Safety & Health Review Commission",
      "Average Errors per Page": 1.0,
      "Form - Initial Findings": 0,
      "pages_count": 1
    },
    {
      "HTML Attribute - Initial Findings": 0,
      "Color Contrast - Initial Findings": 0,
      "Missing Image Descriptions": 0,
      "agency": "Federal Communications Commission",
      "Average Errors per Page": 0.0,
      "Form - Initial Findings": 0,
      "pages_count": 3
    },
    {
      "HTML Attribute - Initial Findings": 0,
      "Color Contrast - Initial Findings": 0,
      "Missing Image Descriptions": 0,
      "agency": "Defense Nuclear Facilities Safety Board",
      "Average Errors per Page": 0.0,
      "Form - Initial Findings": 0,
      "pages_count": 1
    },
    {
      "HTML Attribute - Initial Findings": 0,
      "Color Contrast - Initial Findings": 0,
      "Missing Image Descriptions": 0,
      "agency": "Department of State OIG",
      "Average Errors per Page": 0.0,
      "Form - Initial Findings": 0,
      "pages_count": 1
    },
    {
      "HTML Attribute - Initial Findings": 0,
      "Color Contrast - Initial Findings": 4,
      "Missing Image Descriptions": 0,
      "agency": "Medical Payment Advisory Commission",
      "Average Errors per Page": 4.0,
      "Form - Initial Findings": 0,
      "pages_count": 1
    },
    {
      "HTML Attribute - Initial Findings": 9,
      "Color Contrast - Initial Findings": 12,
      "Missing Image Descriptions": 0,
      "agency": "Gulf Coast Ecosystem Restoration Council (GCERC)",
      "Average Errors per Page": 21.0,
      "Form - Initial Findings": 0,
      "pages_count": 1
    },
    {
      "HTML Attribute - Initial Findings": 0,
      "Color Contrast - Initial Findings": 0,
      "Missing Image Descriptions": 0,
      "agency": "Equal Employment Opportunity Commission",
      "Average Errors per Page": 0.0,
      "Form - Initial Findings": 0,
      "pages_count": 1
    },
    {
      "HTML Attribute - Initial Findings": 0.31,
      "Color Contrast - Initial Findings": 1.08,
      "Missing Image Descriptions": 0.69,
      "agency": "Department of Labor",
      "Average Errors per Page": 2.08,
      "Form - Initial Findings": 0,
      "pages_count": 13
    },
    {
      "HTML Attribute - Initial Findings": 0.67,
      "Color Contrast - Initial Findings": 0,
      "Missing Image Descriptions": 0,
      "agency": "Department of Housing And Urban Development",
      "Average Errors per Page": 0.67,
      "Form - Initial Findings": 0,
      "pages_count": 3
    }
  ]
}